text_python/__init__.py
text_python/c_ao.py
text_python/core.py
text_python/cpp_ao.py
text_python/gui.py
text_python-1.0.dist-info/METADATA
text_python-1.0.dist-info/WHEEL
text_python-1.0.dist-info/top_level.txt
text_python-1.0.dist-info/RECORD
