Metadata-Version: 2.4
Name: text_python
Version: 1.0
Summary: Thu vien text_python ket hop Python, Pygame, C va C++
Author: Ung
Author-email: Ung <ung@example.com>
Requires-Python: >=3.10
Requires-Dist: pygame>=2.6.1
Dynamic: author
Dynamic: requires-python
